schwarz/column_alchemy/__init__.py
schwarz/column_alchemy/shifted_decimal.py
schwarz/column_alchemy/test_utils.py
schwarz/column_alchemy/utc_datetime_column.py
schwarz/column_alchemy/values_enum.py
schwarz/column_alchemy/yearmonth.py
schwarz/column_alchemy/yearmonth_column.py
schwarz/column_alchemy/tests/__init__.py
schwarz/column_alchemy/tests/int_enums_test.py
schwarz/column_alchemy/tests/shifted_decimal_test.py
schwarz/column_alchemy/tests/utc_datetime_column_test.py
schwarz/column_alchemy/tests/values_enum_test.py
schwarz/column_alchemy/tests/yearmonth_column_test.py
schwarz/column_alchemy/tests/yearmonth_test.py
ColumnAlchemy-0.10.1.dist-info/LICENSE-UTCDateTime.txt
ColumnAlchemy-0.10.1.dist-info/LICENSE.txt
ColumnAlchemy-0.10.1.dist-info/METADATA
ColumnAlchemy-0.10.1.dist-info/WHEEL
ColumnAlchemy-0.10.1.dist-info/top_level.txt
ColumnAlchemy-0.10.1.dist-info/RECORD
