Metadata-Version: 2.2
Name: ColumnAlchemy
Version: 0.10.1
Summary: additional column types for SQLAlchemy
Home-page: https://github.com/FelixSchwarz/column-alchemy
Author: Felix Schwarz
Author-email: felix.schwarz@oss.schwarz.eu
License: MIT
Requires-Python: >=3.6
License-File: LICENSE-UTCDateTime.txt
License-File: LICENSE.txt
Requires-Dist: SQLAlchemy>=1.2.3
Provides-Extra: testing
Requires-Dist: pytest; extra == "testing"
